FusionX/FusionX.py
FusionX/__init__.py
FusionX/helpers/__init__.py
FusionX/helpers/cell_nuclei_assignment.py
FusionX/helpers/cell_nuclei_report.py
FusionX/helpers/cellpose_inference.py
FusionX/helpers/clean_up.py
FusionX/helpers/console_print.py
FusionX/helpers/download_cellx.py
FusionX/helpers/file_handlers.py
FusionX/helpers/image_handlers.py
FusionX/helpers/logging_setup.py
FusionX/helpers/membrane_tiler.py
FusionX/helpers/nuclei_analysis.py
FusionX/helpers/nuclei_in_tiles.py
FusionX/helpers/nuclei_recovery.py
FusionX/helpers/nucleus_centric_cellx.py
FusionX/helpers/progress_bar.py
FusionX/helpers/validation.py
FusionX/helpers/visualization.py
FusionX/segment_anything_custom/__init__.py
FusionX/segment_anything_custom/automatic_mask_generator.py
FusionX/segment_anything_custom/build_sam.py
FusionX/segment_anything_custom/predictor.py
FusionX/segment_anything_custom/modeling/__init__.py
FusionX/segment_anything_custom/modeling/common.py
FusionX/segment_anything_custom/modeling/image_encoder.py
FusionX/segment_anything_custom/modeling/mask_decoder.py
FusionX/segment_anything_custom/modeling/prompt_encoder.py
FusionX/segment_anything_custom/modeling/sam.py
FusionX/segment_anything_custom/modeling/transformer.py
FusionX/segment_anything_custom/utils/__init__.py
FusionX/segment_anything_custom/utils/amg.py
FusionX/segment_anything_custom/utils/onnx.py
FusionX/segment_anything_custom/utils/transforms.py
fusionx-0.9.12.dist-info/METADATA
fusionx-0.9.12.dist-info/WHEEL
fusionx-0.9.12.dist-info/entry_points.txt
fusionx-0.9.12.dist-info/top_level.txt
fusionx-0.9.12.dist-info/RECORD
