Metadata-Version: 2.4
Name: fusionx
Version: 0.9.12
Summary: Segmentation and counting nuclei of fused cells
Author: Suman Khan
Author-email: suman.khan@weizmann.ac.il
Classifier: Programming Language :: Python :: 3
Requires-Python: >=3.10
Requires-Dist: opencv-python==4.10.0.84
Requires-Dist: numba==0.60.0
Requires-Dist: numpy==1.26.4
Requires-Dist: pandas==2.2.2
Requires-Dist: pycocotools==2.0.8
Requires-Dist: scipy==1.14.0
Requires-Dist: tifffile==2024.8.10
Requires-Dist: torch==2.6.0
Requires-Dist: torchvision==0.21.0
Requires-Dist: tqdm==4.66.5
Requires-Dist: requests==2.32.5
Requires-Dist: cellpose==3.0.11
Requires-Dist: pyarrow==17.0.0
Dynamic: author
Dynamic: author-email
Dynamic: classifier
Dynamic: requires-dist
Dynamic: requires-python
Dynamic: summary
